zerolog/__init__.py
zerolog/_globals.py
zerolog/console.py
zerolog/constants.py
zerolog/context.py
zerolog/encoder.py
zerolog/encoder_json.py
zerolog/event.py
zerolog/hook.py
zerolog/level.py
zerolog/logger.py
zerolog/sampler.py
zerolog/stacktrace.py
zerolog/time.py
zerolog/internal/__init__.py
zerolog/internal/json/__init__.py
zerolog/internal/json/json.py
zerolog/internal/util/__init__.py
zerolog/internal/util/atomic.py
zerolog/internal/util/time.py
zerolog/log/__init__.py
zerolog/log/log.py
python_zerolog-0.1.0.dist-info/LICENSE
python_zerolog-0.1.0.dist-info/METADATA
python_zerolog-0.1.0.dist-info/WHEEL
python_zerolog-0.1.0.dist-info/top_level.txt
python_zerolog-0.1.0.dist-info/RECORD
