Metadata-Version: 2.1
Name: python-zerolog
Version: 0.1.0
Summary: Zero setup JSON logger
Home-page: https://github.com/alexferl/zerolog
Author: Alexandre Ferland
Author-email: me@alexferl.com
License: MIT
Classifier: Intended Audience :: Developers
Classifier: License :: OSI Approved :: MIT License
Classifier: Operating System :: OS Independent
Classifier: Programming Language :: Python :: 3.11
Classifier: Topic :: Software Development :: Libraries :: Python Modules
Requires-Python: >=3.11
License-File: LICENSE
Requires-Dist: python-dateutil >=2.8.2
Requires-Dist: types-python-dateutil >=2.8.19.14
